{
  "option": "a",
  "start_year": 2015,
  "n_episodes": 220,
  "fee_bps": 10,
  "lookback": 20,
  "state_size": 3048,
  "n_features": 152,
  "n_etfs": 7,
  "trained_at": "2026-04-15T07:58:01.982645",
  "best_val_sharpe": 1.8584,
  "test_sharpe": 1.6668,
  "test_equity": 1.1638,
  "train_days": 2248,
  "val_days": 263,
  "test_days": 265,
  "history": [
    {
      "episode": 201,
      "train_sharpe": 10.28,
      "train_equity": 171530.7111,
      "val_sharpe": 0.738,
      "val_equity": 1.1146,
      "avg_loss": 0.00018,
      "epsilon": 0.2358
    },
    {
      "episode": 202,
      "train_sharpe": 10.048,
      "train_equity": 611663.8103,
      "val_sharpe": 0.056,
      "val_equity": 1.0356,
      "avg_loss": 0.000172,
      "epsilon": 0.231
    },
    {
      "episode": 203,
      "train_sharpe": 10.539,
      "train_equity": 50778.9197,
      "val_sharpe": 0.442,
      "val_equity": 1.1312,
      "avg_loss": 0.000171,
      "epsilon": 0.2275
    },
    {
      "episode": 204,
      "train_sharpe": 10.927,
      "train_equity": 25603.1902,
      "val_sharpe": 0.364,
      "val_equity": 1.092,
      "avg_loss": 0.000171,
      "epsilon": 0.2242
    },
    {
      "episode": 205,
      "train_sharpe": 10.52,
      "train_equity": 10881.8252,
      "val_sharpe": -0.003,
      "val_equity": 1.0492,
      "avg_loss": 0.000169,
      "epsilon": 0.2215
    },
    {
      "episode": 206,
      "train_sharpe": 10.259,
      "train_equity": 111620.4802,
      "val_sharpe": -0.272,
      "val_equity": 0.9765,
      "avg_loss": 0.000168,
      "epsilon": 0.2175
    },
    {
      "episode": 207,
      "train_sharpe": 10.965,
      "train_equity": 123985.3112,
      "val_sharpe": -0.451,
      "val_equity": 0.9873,
      "avg_loss": 0.000164,
      "epsilon": 0.2136
    },
    {
      "episode": 208,
      "train_sharpe": 10.45,
      "train_equity": 24805.6971,
      "val_sharpe": 0.977,
      "val_equity": 1.1867,
      "avg_loss": 0.000161,
      "epsilon": 0.2104
    },
    {
      "episode": 209,
      "train_sharpe": 10.722,
      "train_equity": 1039612.7869,
      "val_sharpe": 0.358,
      "val_equity": 1.0368,
      "avg_loss": 0.000162,
      "epsilon": 0.2057
    },
    {
      "episode": 210,
      "train_sharpe": 10.716,
      "train_equity": 7390.4881,
      "val_sharpe": -0.881,
      "val_equity": 0.9484,
      "avg_loss": 0.000165,
      "epsilon": 0.2029
    },
    {
      "episode": 211,
      "train_sharpe": 10.668,
      "train_equity": 1696899.5636,
      "val_sharpe": 0.357,
      "val_equity": 1.069,
      "avg_loss": 0.000177,
      "epsilon": 0.1978
    },
    {
      "episode": 212,
      "train_sharpe": 10.093,
      "train_equity": 172976.7822,
      "val_sharpe": -1.207,
      "val_equity": 0.9288,
      "avg_loss": 0.000157,
      "epsilon": 0.1936
    },
    {
      "episode": 213,
      "train_sharpe": 11.168,
      "train_equity": 963697.8493,
      "val_sharpe": -0.553,
      "val_equity": 0.9416,
      "avg_loss": 0.000159,
      "epsilon": 0.189
    },
    {
      "episode": 214,
      "train_sharpe": 11.456,
      "train_equity": 12819.7953,
      "val_sharpe": -0.384,
      "val_equity": 0.9834,
      "avg_loss": 0.000154,
      "epsilon": 0.1864
    },
    {
      "episode": 215,
      "train_sharpe": 11.136,
      "train_equity": 3774661.6804,
      "val_sharpe": -0.422,
      "val_equity": 0.9765,
      "avg_loss": 0.000158,
      "epsilon": 0.1814
    },
    {
      "episode": 216,
      "train_sharpe": 11.604,
      "train_equity": 169081.44,
      "val_sharpe": -1.094,
      "val_equity": 0.9001,
      "avg_loss": 0.000157,
      "epsilon": 0.1777
    },
    {
      "episode": 217,
      "train_sharpe": 11.428,
      "train_equity": 2585089.9825,
      "val_sharpe": 0.19,
      "val_equity": 1.0398,
      "avg_loss": 0.000152,
      "epsilon": 0.1729
    },
    {
      "episode": 218,
      "train_sharpe": 11.204,
      "train_equity": 20171.6719,
      "val_sharpe": -0.036,
      "val_equity": 1.0265,
      "avg_loss": 0.000147,
      "epsilon": 0.1701
    },
    {
      "episode": 219,
      "train_sharpe": 12.418,
      "train_equity": 139656.7275,
      "val_sharpe": -0.948,
      "val_equity": 0.9271,
      "avg_loss": 0.000152,
      "epsilon": 0.1667
    },
    {
      "episode": 220,
      "train_sharpe": 12.266,
      "train_equity": 25099.2932,
      "val_sharpe": -0.659,
      "val_equity": 0.8983,
      "avg_loss": 0.000148,
      "epsilon": 0.164
    }
  ]
}